.VERSION
AUTHORS.rst
CONTRIBUTING.rst
HISTORY.rst
LICENSE
MANIFEST.in
Pipfile
Pipfile.lock
README.rst
USAGE.rst
dev-requirements.txt
requirements.txt
setup.cfg
setup.py
docs/Makefile
docs/authors.rst
docs/conf.py
docs/contributing.rst
docs/history.rst
docs/index.rst
docs/installation.rst
docs/readme.rst
docs/usage.rst
wikiserieswillemcli/.VERSION
wikiserieswillemcli/AUTHORS.rst
wikiserieswillemcli/CONTRIBUTING.rst
wikiserieswillemcli/HISTORY.rst
wikiserieswillemcli/LICENSE
wikiserieswillemcli/Pipfile
wikiserieswillemcli/Pipfile.lock
wikiserieswillemcli/README.rst
wikiserieswillemcli/USAGE.rst
wikiserieswillemcli/__init__.py
wikiserieswillemcli/_version.py
wikiserieswillemcli/dev-requirements.txt
wikiserieswillemcli/requirements.txt
wikiserieswillemcli/wikiserieswillemcli.py
wikiserieswillemcli/wikiserieswillemcliexceptions.py
wikiserieswillemcli.egg-info/PKG-INFO
wikiserieswillemcli.egg-info/SOURCES.txt
wikiserieswillemcli.egg-info/dependency_links.txt
wikiserieswillemcli.egg-info/entry_points.txt
wikiserieswillemcli.egg-info/not-zip-safe
wikiserieswillemcli.egg-info/requires.txt
wikiserieswillemcli.egg-info/top_level.txt
wikiserieswillemcli/__pycache__/__init__.cpython-39.pyc
wikiserieswillemcli/__pycache__/_version.cpython-39.pyc
wikiserieswillemcli/__pycache__/wikiserieswillemcliexceptions.cpython-39.pyc
wikiserieswillemcli/conf/__init__.py
wikiserieswillemcli/conf/configuration.py
wikiserieswillemcli/conf/logging.json-example
wikiserieswillemcli/conf/__pycache__/__init__.cpython-39.pyc
wikiserieswillemcli/conf/__pycache__/configuration.cpython-39.pyc