Metadata-Version: 2.1
Name: wikiserieswillemcli
Version: 0.1.1
Summary: A template to create python libraries
Home-page: https://github.com/wmkuipers/wikiserieswillemcli
Author: Willem Kuipers
Author-email: willem@kuipers.co.uk
License: MIT
Keywords: wikiserieswillemcli
Classifier: Development Status :: 3 - Alpha
Classifier: Intended Audience :: Developers
Classifier: License :: OSI Approved :: MIT License
Classifier: Natural Language :: English
Classifier: Programming Language :: Python :: 3.9
License-File: LICENSE
License-File: AUTHORS.rst
